<?xml version='1.0' encoding='UTF-8' ?>
<!-- was: <?xml version="1.0" encoding="UTF-8"?> -->
<beans xmlns="http://www.springframework.org/schema/beans"
       xmlns:xsi="http://www.w3.org/2001/XMLSchema-instance"
       xmlns:p="http://www.springframework.org/schema/p"
       xmlns:aop="http://www.springframework.org/schema/aop"
       xmlns:tx="http://www.springframework.org/schema/tx"
       xmlns:mvc="http://www.springframework.org/schema/mvc"
       xmlns:task="http://www.springframework.org/schema/task"
       xmlns:context="http://www.springframework.org/schema/context"
       xsi:schemaLocation="http://www.springframework.org/schema/beans http://www.springframework.org/schema/beans/spring-beans-4.0.xsd
       http://www.springframework.org/schema/aop http://www.springframework.org/schema/aop/spring-aop-4.0.xsd
       http://www.springframework.org/schema/tx http://www.springframework.org/schema/tx/spring-tx-4.0.xsd
       http://www.springframework.org/schema/mvc http://www.springframework.org/schema/mvc/spring-mvc-4.0.xsd
       http://www.springframework.org/schema/task http://www.springframework.org/schema/task/spring-task-4.0.xsd
       http://www.springframework.org/schema/context http://www.springframework.org/schema/context/spring-context-4.0.xsd">
    
    <mvc:annotation-driven/>
    
    <!-- Register controllers -->
    <context:component-scan base-package="es.agustruiz.solarforecast"/>
        
    <!-- Dispatching requests to Controllers -->
    <bean id="viewResolver"
          class="org.springframework.web.servlet.view.InternalResourceViewResolver"
          p:prefix="/WEB-INF/jsp/"
          p:suffix=".jsp" />
    
    <!-- Resources files -->
    <mvc:resources mapping="/resources/**" location="/resources/" />
    
    
    <!-- Scheduler -->
    <task:scheduler id="forecastScheduler" pool-size="10" />
    <task:scheduled-tasks scheduler="forecastScheduler">
        <task:scheduled ref="OpenWeatherMapBean" method="scheduledTask" fixed-rate="#{OpenWeatherMapBean.FIXED_RATE}" initial-delay="0" />
    </task:scheduled-tasks>
    <!-- End scheduler -->
    
</beans>
